panda/__init__.py
panda/__main__.py
panda/data/panda.txt
vegu_pandax-0.1.1.dist-info/METADATA
vegu_pandax-0.1.1.dist-info/WHEEL
vegu_pandax-0.1.1.dist-info/top_level.txt
vegu_pandax-0.1.1.dist-info/RECORD
