Metadata-Version: 2.1
Name: vegu-pandax
Version: 0.1.1
Summary: Dummy python package used for testing PyPI releases
Home-page: https://github.com/vegu/panda
Author: vegu
Author-email: stefan@20c.com
License: MIT
Platform: UNKNOWN
Classifier: License :: OSI Approved :: MIT License
Classifier: Programming Language :: Python :: 3
Classifier: Programming Language :: Python :: 3.7
